mcp_tracker/__init__.py
mcp_tracker/__main__.py
mcp_tracker/settings.py
mcp_tracker/mcp/__init__.py
mcp_tracker/mcp/context.py
mcp_tracker/mcp/errors.py
mcp_tracker/mcp/params.py
mcp_tracker/mcp/resources.py
mcp_tracker/mcp/server.py
mcp_tracker/mcp/utils.py
mcp_tracker/mcp/oauth/__init__.py
mcp_tracker/mcp/oauth/provider.py
mcp_tracker/mcp/oauth/store.py
mcp_tracker/mcp/oauth/types.py
mcp_tracker/mcp/oauth/stores/__init__.py
mcp_tracker/mcp/oauth/stores/crypto.py
mcp_tracker/mcp/oauth/stores/memory.py
mcp_tracker/mcp/oauth/stores/redis.py
mcp_tracker/mcp/oauth/stores/serializers.py
mcp_tracker/mcp/tools/__init__.py
mcp_tracker/mcp/tools/_access.py
mcp_tracker/mcp/tools/field.py
mcp_tracker/mcp/tools/issue_read.py
mcp_tracker/mcp/tools/issue_write.py
mcp_tracker/mcp/tools/queue.py
mcp_tracker/mcp/tools/user.py
mcp_tracker/tracker/__init__.py
mcp_tracker/tracker/caching/__init__.py
mcp_tracker/tracker/caching/client.py
mcp_tracker/tracker/custom/__init__.py
mcp_tracker/tracker/custom/client.py
mcp_tracker/tracker/custom/errors.py
mcp_tracker/tracker/proto/__init__.py
mcp_tracker/tracker/proto/common.py
mcp_tracker/tracker/proto/fields.py
mcp_tracker/tracker/proto/issues.py
mcp_tracker/tracker/proto/queues.py
mcp_tracker/tracker/proto/users.py
mcp_tracker/tracker/proto/types/__init__.py
mcp_tracker/tracker/proto/types/base.py
mcp_tracker/tracker/proto/types/fields.py
mcp_tracker/tracker/proto/types/inputs.py
mcp_tracker/tracker/proto/types/issue_types.py
mcp_tracker/tracker/proto/types/issues.py
mcp_tracker/tracker/proto/types/mixins.py
mcp_tracker/tracker/proto/types/priorities.py
mcp_tracker/tracker/proto/types/queues.py
mcp_tracker/tracker/proto/types/refs.py
mcp_tracker/tracker/proto/types/resolutions.py
mcp_tracker/tracker/proto/types/statuses.py
mcp_tracker/tracker/proto/types/users.py
yandex_tracker_mcp-0.6.2.dist-info/licenses/LICENSE
yandex_tracker_mcp-0.6.2.dist-info/METADATA
yandex_tracker_mcp-0.6.2.dist-info/WHEEL
yandex_tracker_mcp-0.6.2.dist-info/entry_points.txt
yandex_tracker_mcp-0.6.2.dist-info/top_level.txt
yandex_tracker_mcp-0.6.2.dist-info/RECORD
